odincontrib_aws/__init__.py
odincontrib_aws/dynamodb/__init__.py
odincontrib_aws/dynamodb/exceptions.py
odincontrib_aws/dynamodb/fields.py
odincontrib_aws/dynamodb/indexes.py
odincontrib_aws/dynamodb/query.py
odincontrib_aws/dynamodb/session.py
odincontrib_aws/dynamodb/table.py
odincontrib_aws/dynamodb/types.py
odincontrib_aws/dynamodb/utils.py
odincontrib.aws-0.4.1.dist-info/WHEEL
odincontrib.aws-0.4.1.dist-info/METADATA
odincontrib.aws-0.4.1.dist-info/RECORD
