Metadata-Version: 2.1
Name: odincontrib.aws
Version: 0.4.1
Summary: Odin integration with AWS
Home-page: https://github.com/python-odin/odin.contrib-dynamodb
License: BSD-3-Clause
Keywords: aws,dynamodb,sqs,data-structure,validation,data-mapping
Author: Tim Savage
Author-email: tim@savage.company
Requires-Python: >=3.6,<3.10
Classifier: Development Status :: 5 - Production/Stable
Classifier: Intended Audience :: Developers
Classifier: License :: OSI Approved :: BSD License
Classifier: Operating System :: OS Independent
Classifier: Programming Language :: Python
Classifier: Programming Language :: Python :: 2
Classifier: Programming Language :: Python :: 2.7
Classifier: Programming Language :: Python :: 3
Classifier: Programming Language :: Python :: 3.6
Classifier: Programming Language :: Python :: 3.7
Classifier: Programming Language :: Python :: 3.8
Classifier: Programming Language :: Python :: 3.9
Classifier: Programming Language :: Python :: Implementation :: CPython
Classifier: Programming Language :: Python :: Implementation :: PyPy
Classifier: Topic :: Software Development :: Libraries :: Application Frameworks
Classifier: Topic :: Software Development :: Libraries :: Python Modules
Requires-Dist: boto3 (>=1,<2)
Requires-Dist: odin (>=1,<2)
Requires-Dist: six
Project-URL: Repository, https://github.com/python-odin/odin.contrib-dynamodb
